CHANGES.txt
LICENSE.txt
MANIFEST.in
README.rst
setup.py
auto_version/__init__.py
auto_version/dvcs.py
auto_version/main.py
auto_version/parsers.py
auto_version/styles.py
auto_version/utils.py
auto_version.egg-info/PKG-INFO
auto_version.egg-info/SOURCES.txt
auto_version.egg-info/dependency_links.txt
auto_version.egg-info/entry_points.txt
auto_version.egg-info/top_level.txt
docs/index.rst
docs/organisation.rst