Metadata-Version: 1.1
Name: auto-version
Version: 0.1.3
Summary: A not-so-simple versioning semi-automation.
Home-page: https://github.com/paulollivier/auto-version
Author: Paul Ollivier
Author-email: contact@paulollivier.fr
License:                    GNU LESSER GENERAL PUBLIC LICENSE
